locknkey/__init__.py
locknkey/__main__.py
locknkey/auth.py
locknkey/client.py
locknkey/config.py
locknkey/crypto.py
locknkey/main.py
locknkey/service_token.py
locknkey/vault.py
locknkeycmd-0.2.0.dist-info/METADATA
locknkeycmd-0.2.0.dist-info/WHEEL
locknkeycmd-0.2.0.dist-info/entry_points.txt
locknkeycmd-0.2.0.dist-info/top_level.txt
locknkeycmd-0.2.0.dist-info/RECORD
