Metadata-Version: 2.4
Name: locknkeycmd
Version: 0.2.0
Summary: Official CLI for LocknKey - Secure, Zero-Knowledge Secret Management with environment injection.
Author-email: Locknkey Team <thiskaranpatel@gmail.com>
Requires-Python: >=3.9
Requires-Dist: typer[all]
Requires-Dist: firebase-admin
Requires-Dist: pynacl
Requires-Dist: keyring
Requires-Dist: google-auth-oauthlib
Requires-Dist: requests
Requires-Dist: rich
Requires-Dist: pyotp
Requires-Dist: pyfiglet
